eplatform/__init__.py
eplatform/_controller.py
eplatform/_display.py
eplatform/_eplatform.c
eplatform/_eplatform.cpython-312-darwin.so
eplatform/_eplatform.cpython-313-darwin.so
eplatform/_eplatform.pyi
eplatform/_event_loop.py
eplatform/_keyboard.py
eplatform/_mouse.py
eplatform/_platform.py
eplatform/_type.py
eplatform/_window.py
eplatform/_window_icon.py
eplatform/py.typed
eplatform-0.19.1.dist-info/METADATA
eplatform-0.19.1.dist-info/WHEEL
eplatform-0.19.1.dist-info/licenses/LICENSE
eplatform-0.19.1.dist-info/RECORD
