Metadata-Version: 2.4
Name: eplatform
Version: 0.19.1
Summary: Operating System Library
License-File: LICENSE
Author: Erik Soma
Author-email: stillusingirc@gmail.com
Requires-Python: >=3.12
Classifier: Programming Language :: Python :: 3
Classifier: Programming Language :: Python :: 3.12
Classifier: Programming Language :: Python :: 3.13
Classifier: Programming Language :: Python :: 3.14
Requires-Dist: eevent (>=0,<1)
Requires-Dist: egeometry (>=0,<1)
Requires-Dist: emath (>=0,<1)
